{
  "featuresList": [
    {
      "feature": "Centralized Database",
      "text": "Files are hashed and compared against AniDB's database to find the correct episode and series.",
      "faLink": "fas fa-server"
    },
    {
      "feature": "File Management",
      "text": "Easily handle multiple, duplicate and missing files within your collection using our built-in utilities.",
      "faLink": "fas fa-copy"
    },
    {
      "feature": "Media Player Support",
      "text": "Shoko integrates with Plex, Kodi & MediaPortal allowing you to watch your collection wherever you'd like.",
      "faLink": "fas fa-tv"
    },
    {
      "feature": "Extensive API",
      "text": "Expand the capabilities of Shoko to suite your needs or to bring Shoko to an entirely new platform.",
      "faLink": "fas fa-project-diagram"
    }
  ]
}